miar/__init__.py
miar/_utils.py
miar/measures.py
miar-0.1.1.dist-info/licenses/AUTHORS.rst
miar-0.1.1.dist-info/licenses/LICENSE
miar-0.1.1.dist-info/METADATA
miar-0.1.1.dist-info/WHEEL
miar-0.1.1.dist-info/top_level.txt
miar-0.1.1.dist-info/RECORD
