Metadata-Version: 2.4
Name: miar
Version: 0.1.1
Summary: A Python project for interestingness measures of association rules
Author-email: Matej Benes <mate.benes@gmail.com>
Maintainer-email: Matej Benes <mate.benes@gmail.com>
License: MIT license
Project-URL: bugs, https://github.com/M-Benes/miar/issues
Project-URL: changelog, https://github.com/M-Benes/miar/blob/master/changelog.md
Project-URL: homepage, https://github.com/M-Benes/miar
License-File: LICENSE
License-File: AUTHORS.rst
Provides-Extra: dev
Requires-Dist: coverage; extra == "dev"
Requires-Dist: mypy; extra == "dev"
Requires-Dist: pytest; extra == "dev"
Requires-Dist: ruff; extra == "dev"
Dynamic: license-file
